netsuite/__init__.py
netsuite/cli/__init__.py
netsuite/cli/helpers.py
netsuite/cli/interact.py
netsuite/cli/main.py
netsuite/cli/misc.py
netsuite/cli/rest_api.py
netsuite/cli/restlet.py
netsuite/cli/soap_api.py
netsuite/client.py
netsuite/config.py
netsuite/constants.py
netsuite/exceptions.py
netsuite/json.py
netsuite/rest_api.py
netsuite/rest_api_base.py
netsuite/restlet.py
netsuite/soap_api/__init__.py
netsuite/soap_api/client.py
netsuite/soap_api/decorators.py
netsuite/soap_api/exceptions.py
netsuite/soap_api/helpers.py
netsuite/soap_api/passport.py
netsuite/soap_api/transports.py
netsuite/soap_api/zeep.py
netsuite-0.12.0.dist-info/LICENSE
netsuite-0.12.0.dist-info/METADATA
netsuite-0.12.0.dist-info/WHEEL
netsuite-0.12.0.dist-info/entry_points.txt
netsuite-0.12.0.dist-info/RECORD
